pydantic_adobe_audition/__init__.py
pydantic_adobe_audition/common.py
pydantic_adobe_audition/model/__init__.py
pydantic_adobe_audition/model/audio_device.py
pydantic_adobe_audition/model/files.py
pydantic_adobe_audition/model/common/__init__.py
pydantic_adobe_audition/model/common/channel_map.py
pydantic_adobe_audition/model/common/edit_parameter.py
pydantic_adobe_audition/model/session/__init__.py
pydantic_adobe_audition/model/session/clip_groups.py
pydantic_adobe_audition/model/session/metronome.py
pydantic_adobe_audition/model/session/properties.py
pydantic_adobe_audition/model/session/state.py
pydantic_adobe_audition/model/session/tracks/__init__.py
pydantic_adobe_audition/model/session/tracks/audio/__init__.py
pydantic_adobe_audition/model/session/tracks/audio/audio_clip/__init__.py
pydantic_adobe_audition/model/session/tracks/audio/audio_clip/fade.py
pydantic_adobe_audition/model/session/tracks/audio/audio_clip/properties.py
pydantic_adobe_audition/model/session/tracks/bus/__init__.py
pydantic_adobe_audition/model/session/tracks/common/__init__.py
pydantic_adobe_audition/model/session/tracks/common/component.py
pydantic_adobe_audition/model/session/tracks/common/effects_rack.py
pydantic_adobe_audition/model/session/tracks/common/track_audio_parameters.py
pydantic_adobe_audition/model/session/tracks/common/track_parameters.py
pydantic_adobe_audition/model/session/tracks/master/__init__.py
pydantic_adobe_audition/model/session/tracks/metronome/__init__.py
pydantic_adobe_audition-0.1.1.dist-info/WHEEL
pydantic_adobe_audition-0.1.1.dist-info/METADATA
pydantic_adobe_audition-0.1.1.dist-info/RECORD
