Metadata-Version: 2.3
Name: pydantic-adobe-audition
Version: 0.1.1
Summary: Pydantic model for Adobe Audition Sesx project files.
Requires-Python: >=3.10
Requires-Dist: pydantic>=2
Requires-Dist: pydantic-xml
